{"timestamp":"2014-05-23 16:54:19",
 "type":"gallery",
 "title":"Molstraat 2014",
 "slug":"verbouwing-2014",
 "text":"We had some work done to make our home nicer still.",
 "photos":
[{"name":"verbouwing-2014.001", "size":[3264, 2448]}
,{"name":"verbouwing-2014.002", "size":[3264, 2448]}
,{"name":"verbouwing-2014.003", "size":[3264, 2448]}
,{"name":"verbouwing-2014.004", "size":[2448, 3264]}
,{"name":"verbouwing-2014.005", "size":[3264, 2448]}
,{"name":"verbouwing-2014.006", "size":[2448, 3264]}
,{"name":"verbouwing-2014.007", "size":[2448, 3264]}
,{"name":"verbouwing-2014.008", "size":[800, 600]}
,{"name":"verbouwing-2014.009", "size":[2448, 3264]}
,{"name":"verbouwing-2014.010", "size":[3264, 2448]}
,{"name":"verbouwing-2014.011", "size":[3264, 2448]}
,{"name":"verbouwing-2014.012", "size":[3264, 2448]}
,{"name":"verbouwing-2014.013", "size":[3264, 2448]}
,{"name":"verbouwing-2014.014", "size":[2448, 3264]}
,{"name":"verbouwing-2014.015", "size":[2448, 3264]}
]
}